geci_streamlit/__init__.py
geci_streamlit/transformations.py
geci_streamlit-0.4.0.dist-info/LICENSE
geci_streamlit-0.4.0.dist-info/WHEEL
geci_streamlit-0.4.0.dist-info/METADATA
geci_streamlit-0.4.0.dist-info/RECORD
