Metadata-Version: 2.1
Name: geci_streamlit
Version: 0.4.0
Summary: A template Python module
Home-page: https://github.com/IslasGECI/geci_streamlit
Author: Ciencia de Datos • GECI
Author-email: ciencia.datos@islas.org.mx
Requires-Python: >=3.9
Classifier: License :: OSI Approved :: GNU General Public License v3 or later (GPLv3+)
Requires-Dist: descarga-datos==0.*
Requires-Dist: streamlit
